MANIFEST.in
setup.py
aggregate/__init__.py
aggregate/client.py
aggregate/server.py
django_live_profiler.egg-info/PKG-INFO
django_live_profiler.egg-info/SOURCES.txt
django_live_profiler.egg-info/dependency_links.txt
django_live_profiler.egg-info/entry_points.txt
django_live_profiler.egg-info/requires.txt
django_live_profiler.egg-info/top_level.txt
profiler/__init__.py
profiler/instrument.py
profiler/middleware.py
profiler/models.py
profiler/tests.py
profiler/urls.py
profiler/views.py
profiler/static/profiler/bootstrap.css
profiler/static/profiler/jquery-1.7.2.min.js
profiler/static/profiler/jquery.tablesorter.min.js
profiler/static/profiler/profiler.css
profiler/static/profiler/profiler.js
profiler/templates/profiler/base.html
profiler/templates/profiler/by_view.html
profiler/templates/profiler/code.html
profiler/templates/profiler/code.html~
profiler/templates/profiler/index.html
profiler/templates/profiler/reset.html