Metadata-Version: 1.0
Name: django-live-profiler
Version: 0.0.9
Summary: A database access profiler for Django-based applications that can be ran in production with minimal performace overhead.
Home-page: https://github.com/InviteBox/django-live-profiler
Author: Alexander Tereshkin
Author-email: atereshkin@invitebox.com
License: BSD
Keywords: django profiler
Platform: UNKNOWN
Classifier: Development Status :: 3 - Alpha
Classifier: Topic :: Software Development
Classifier: Framework :: Django
Classifier: Intended Audience :: Developers
Classifier: License :: OSI Approved :: BSD License
